lok/__init__.py
lok/admin.py
lok/apps.py
lok/bouncer/__init__.py
lok/bouncer/bounced.py
lok/bouncer/utils.py
lok/enums.py
lok/management/__init__.py
lok/management/commands/__init__.py
lok/management/commands/ensureadmin.py
lok/middlewares/__init__.py
lok/middlewares/request/__init__.py
lok/middlewares/request/bouncer.py
lok/middlewares/request/jwt.py
lok/middlewares/scope/__init__.py
lok/middlewares/scope/bouncer.py
lok/middlewares/scope/jwt.py
lok/middlewares/utils.py
lok/migrations/0001_initial.py
lok/migrations/__init__.py
lok/models.py
lok/tests.py
lok/token.py
lok/utils.py
lok/views.py
lok-0.2.0.dist-info/WHEEL
lok-0.2.0.dist-info/METADATA
lok-0.2.0.dist-info/RECORD
