Metadata-Version: 2.1
Name: lok
Version: 0.2.0
Summary: lok is a jwt middleware that works with django channels
License: CC BY-NC 3.0
Author: jhnnsrs
Author-email: jhnnsrs@gmail.com
Requires-Python: >=3.8,<4.0
Classifier: License :: Other/Proprietary License
Classifier: Programming Language :: Python :: 3
Classifier: Programming Language :: Python :: 3.8
Classifier: Programming Language :: Python :: 3.9
Classifier: Programming Language :: Python :: 3.10
Requires-Dist: Django (>=3.2.7,<4.0.0)
Requires-Dist: PyJWT (>=2.1.0,<3.0.0)
